abstract_flask/__init__.py
abstract_flask/abstract_flask.py
abstract_flask/file_utils.py
abstract_flask/network_tools.py
abstract_flask/request_utils.py
abstract_flask/file_utils/__init__.py
abstract_flask/file_utils/file_utils.py
abstract_flask/file_utils/imports.py
abstract_flask/file_utils/request_files.py
abstract_flask/generator/__init__.py
abstract_flask/generator/generateFlaskRoute.py
abstract_flask/generator/help_utils.py
abstract_flask/network_utils/__init__.py
abstract_flask/network_utils/imports.py
abstract_flask/network_utils/ip_utils.py
abstract_flask/request_utils/__init__.py
abstract_flask/request_utils/call_tracking.py
abstract_flask/request_utils/get_requests.py
abstract_flask/request_utils/imports.py
abstract_flask/request_utils/parse_utils.py
abstract_flask/request_utils/request_utils.py
abstract_flask/user_utils/__init__.py
abstract_flask/user_utils/imports.py
abstract_flask/user_utils/user_utils.py
abstract_flask-0.0.0.1004.dist-info/METADATA
abstract_flask-0.0.0.1004.dist-info/WHEEL
abstract_flask-0.0.0.1004.dist-info/top_level.txt
abstract_flask-0.0.0.1004.dist-info/RECORD
